formattex/__init__.py
formattex/intermediate_repr.py
formattex/nodes.py
formattex/test_dump.py
formattex/test_util.py
formattex/util.py
formattex-0.1.4.dist-info/LICENSE.txt
formattex-0.1.4.dist-info/METADATA
formattex-0.1.4.dist-info/WHEEL
formattex-0.1.4.dist-info/entry_points.txt
formattex-0.1.4.dist-info/top_level.txt
formattex-0.1.4.dist-info/RECORD
